{
    "instance": {
        "updatesDisabled": false,
        "latestVersion": "1.0.0",
        "latestUrl": "https://downloads.nefarius.at/other/nefarius/vpatch/vpatch.exe"
    },
    "shared": {
        "productName": "HidHide",
        "windowTitle": "HidHide Updater",
        "detectionMethod": "RegistryValue",
        "detection": {
            "hive": "HKLM",
            "key": "SOFTWARE\\Nefarius Software Solutions e.U.\\HidHide",
            "value": "Version",

            "path": "F:\\Downloads\\ep_setup (4).exe",
            "algorithm": "SHA1",
            "hash": "6A697E5076A040DB00174D4799D5B8F788D3BC37",

            "size": 1944064
        }
    },
    "releases": [
        {
            "name": "test1",
            "publishedAt": "2023-09-20T13:05:40Z",
            "version": "3.0.0",
            "summary": "## Features\n  * Awesome new thing\n  * Also this\n  * And that\n\n## Bugfixes\n  * Removed bug I put there\n  * Ooopsie, that wasn't supposed to happen\n## Nonsense\n  * Need to see\n  * What happens...\n  * If we need scroll bars\n  * Vertically",
            "downloadUrl": "https://download.visualstudio.microsoft.com/download/pr/f9ea536d-8e1f-4247-88b8-e79e33fa0873/c06e39f73a3bb1ec8833bb1cde98fce3/windowsdesktop-runtime-7.0.12-win-x64.exe",
            "launchArguments": "/norestart",
            "exitCode": {
                "skipCheck": true,
                "successCodes": [
                    0,
                    3010
                ]
            }
        }
    ]
}